ptools_bin/10x_bam2fastq.py
ptools_bin/PrintSequence.py
ptools_bin/PrintTransSequence.py
ptools_bin/__init__.py
ptools_bin/compress.py
ptools_bin/createDiff.py
ptools_bin/getSeq_genome_wN.py
ptools_bin/getSeq_genome_woN.py
ptools_bin/make_unique.py
ptools_bin/pbam2bam.py
ptools_bin/pbam_mapped_transcriptome.py
ptools_bin/print_unique.py
ptools_bin-0.0.7.data/scripts/makeBAM.sh
ptools_bin-0.0.7.data/scripts/makeDiff.sh
ptools_bin-0.0.7.data/scripts/makeFastq.sh
ptools_bin-0.0.7.data/scripts/makepBAM_genome.sh
ptools_bin-0.0.7.data/scripts/makepBAM_transcriptome.sh
ptools_bin-0.0.7.dist-info/LICENSE
ptools_bin-0.0.7.dist-info/METADATA
ptools_bin-0.0.7.dist-info/WHEEL
ptools_bin-0.0.7.dist-info/entry_points.txt
ptools_bin-0.0.7.dist-info/top_level.txt
ptools_bin-0.0.7.dist-info/RECORD
