Metadata-Version: 2.1
Name: ptools-bin
Version: 0.0.7
Summary: Installation for ptools scripts
Home-page: https://github.com/ENCODE-DCC/ptools_bin
Author: Otto Jolanki
Author-email: ojolanki@stanford.edu
License: MIT
Project-URL: Source Code, https://github.com/ENCODE-DCC/ptools_bin
Project-URL: Issue Tracker, https://github.com/ENCODE-DCC/ptools_bin/issues
Platform: UNKNOWN
Classifier: License :: OSI Approved :: MIT License
Classifier: Natural Language :: English
Classifier: Operating System :: OS Independent
Classifier: Programming Language :: Python
Classifier: Programming Language :: Python :: 3
Classifier: Programming Language :: Python :: 3.6
Classifier: Programming Language :: Python :: 3.7
Classifier: Programming Language :: Python :: 3.8
Classifier: Programming Language :: Python :: Implementation :: CPython
Requires-Python: >=3.5
Requires-Dist: numpy (>=1.19.2)
Requires-Dist: biopython (>=1.78)
Requires-Dist: pandas (>=1.1.3)
